awslabs/__init__.py
awslabs/mcp_cost_analysis_expert/__init__.py
awslabs/mcp_cost_analysis_expert/cdk_analyzer.py
awslabs/mcp_cost_analysis_expert/helpers.py
awslabs/mcp_cost_analysis_expert/report_generator.py
awslabs/mcp_cost_analysis_expert/server.py
awslabs/mcp_cost_analysis_expert/static/COST_REPORT_TEMPLATE.md
awslabs/mcp_cost_analysis_expert/static/__init__.py
awslabs/mcp_cost_analysis_expert/static/patterns/BEDROCK.md
awslabs/mcp_cost_analysis_expert/static/patterns/__init__.py
awslabs_mcp_cost_analysis_expert-0.0.10023.dist-info/METADATA
awslabs_mcp_cost_analysis_expert-0.0.10023.dist-info/WHEEL
awslabs_mcp_cost_analysis_expert-0.0.10023.dist-info/entry_points.txt
awslabs_mcp_cost_analysis_expert-0.0.10023.dist-info/RECORD
